acaciamc/__init__.py
acaciamc/__main__.py
acaciamc/ast.py
acaciamc/cli.py
acaciamc/compiler.py
acaciamc/constants.py
acaciamc/error.py
acaciamc/localization.py
acaciamc/parser.py
acaciamc/tokenizer.py
acaciamc/lang/en_US.lang
acaciamc/mccmdgen/__init__.py
acaciamc/mccmdgen/cmds.py
acaciamc/mccmdgen/ctexecuter.py
acaciamc/mccmdgen/ctexpr.py
acaciamc/mccmdgen/datatype.py
acaciamc/mccmdgen/expr.py
acaciamc/mccmdgen/generator.py
acaciamc/mccmdgen/mcselector.py
acaciamc/mccmdgen/optimizer.py
acaciamc/mccmdgen/symbol.py
acaciamc/mccmdgen/utils.py
acaciamc/modules/_math.aca
acaciamc/modules/builtins.py
acaciamc/modules/math.py
acaciamc/modules/music.py
acaciamc/modules/print.py
acaciamc/modules/schedule.py
acaciamc/modules/world.py
acaciamc/objects/__init__.py
acaciamc/objects/boolean.py
acaciamc/objects/entity.py
acaciamc/objects/entity_filter.py
acaciamc/objects/entity_group.py
acaciamc/objects/entity_template.py
acaciamc/objects/extern_egroup.py
acaciamc/objects/float_.py
acaciamc/objects/functions.py
acaciamc/objects/generic.py
acaciamc/objects/integer.py
acaciamc/objects/list_.py
acaciamc/objects/map_.py
acaciamc/objects/module.py
acaciamc/objects/none.py
acaciamc/objects/position.py
acaciamc/objects/position_absolute.py
acaciamc/objects/position_offset.py
acaciamc/objects/rotation.py
acaciamc/objects/string.py
acaciamc/objects/struct.py
acaciamc/objects/struct_template.py
acaciamc/objects/types.py
acaciamc/tools/__init__.py
acaciamc/tools/axe.py
acaciamc/tools/named_tuple.py
acaciamc/tools/resultlib.py
acaciamc/tools/versionlib.py
acaciamc-0.1.0.dist-info/LICENSE
acaciamc-0.1.0.dist-info/METADATA
acaciamc-0.1.0.dist-info/WHEEL
acaciamc-0.1.0.dist-info/entry_points.txt
acaciamc-0.1.0.dist-info/top_level.txt
acaciamc-0.1.0.dist-info/RECORD
