Metadata-Version: 2.1
Name: acaciamc
Version: 0.1.0
Summary: Compiler of Acacia, a programming language for Minecraft BE.
Author: CBerJun
License: MIT License
Project-URL: Repository, https://github.com/CBerJun/AcaciaMC
Keywords: acacia,minecraft,mcfunction
Classifier: Programming Language :: Python :: 3
Classifier: License :: OSI Approved :: MIT License
Classifier: Topic :: Software Development :: Compilers
Requires-Python: >=3.6.1
License-File: LICENSE
